picdetect/__init__.py
picdetect/config.py
picdetect/detect.py
picdetect/model.py
picdetect/utils.py
picdetect/visualize1.py
picdetect-0.1.dist-info/METADATA
picdetect-0.1.dist-info/WHEEL
picdetect-0.1.dist-info/top_level.txt
picdetect-0.1.dist-info/RECORD
