Metadata-Version: 2.1
Name: picdetect
Version: 0.1
Summary: Picture Detect.
Home-page: https://github.com/Zening-Li/picdetect
Author: Ning
Author-email: admin@163.com
License: UNKNOWN
Platform: UNKNOWN
Classifier: Programming Language :: Python :: 3
Classifier: License :: OSI Approved :: MIT License
Classifier: Operating System :: OS Independent
